dnsmule_plugins/__init__.py
dnsmule_plugins/certcheck/__init__.py
dnsmule_plugins/certcheck/adapter.py
dnsmule_plugins/certcheck/certificates.py
dnsmule_plugins/certcheck/domains.py
dnsmule_plugins/certcheck/rule.py
dnsmule_plugins/ipranges/__init__.py
dnsmule_plugins/ipranges/iprange.py
dnsmule_plugins/ipranges/rule.py
dnsmule_plugins/ipranges/providers/__init__.py
dnsmule_plugins/ipranges/providers/_core.py
dnsmule_plugins/ipranges/providers/amazon.py
dnsmule_plugins/ipranges/providers/cloudflare.py
dnsmule_plugins/ipranges/providers/digitalocean.py
dnsmule_plugins/ipranges/providers/google.py
dnsmule_plugins/ipranges/providers/microsoft.py
dnsmule_plugins/ptrscan/__init__.py
dnsmule_plugins/ptrscan/rule.py
dnsmule_plugins-0.5.0.dist-info/METADATA
dnsmule_plugins-0.5.0.dist-info/WHEEL
dnsmule_plugins-0.5.0.dist-info/top_level.txt
dnsmule_plugins-0.5.0.dist-info/RECORD
