Metadata-Version: 2.1
Name: dnsmule-plugins
Version: 0.5.0
Summary: Plugins for DNSMule
Home-page: https://github.com/joniumGit/dnsmule
Author: joniumGit
Author-email: 52005121+joniumGit@users.noreply.github.com
License: MIT
Project-URL: Bug Reports, https://github.com/joniumGit/dnsmule/issues
Project-URL: Source, https://github.com/joniumGit/dnsmule
Keywords: DNS,Dependency,IP,Cloud
Classifier: License :: OSI Approved :: MIT License
Classifier: Programming Language :: Python :: 3
Classifier: Development Status :: 3 - Alpha
Classifier: Intended Audience :: Developers
Classifier: Intended Audience :: Science/Research
Classifier: Topic :: Internet
Requires-Python: >=3.7
Requires-Dist: dnsmule
Provides-Extra: dev
Requires-Dist: pytest ; extra == 'dev'
Requires-Dist: pytest-cov ; extra == 'dev'
Requires-Dist: cryptography ; extra == 'dev'
Provides-Extra: full
Requires-Dist: cryptography ; extra == 'full'
